{
 "0": "https://market.yandex.ru/search?shopPromoId=895958_MPC_1779876080&promo-type-name=promo-code&businessId=895958&promoKey=7z3N4A4fDgr-HnBAt8P9Ag",
 "1": "https://market.yandex.ru/search?shopPromoId=958778_MPC_1775812456&promo-type-name=promo-code&businessId=958778",
 "2": "https://market.yandex.ru/search?shopPromoId=2270294_MPC_1777900468&promo-type-name=promo-code&businessId=2270294",
 "3": "https://market.yandex.ru/search?shopPromoId=208326358_MPC_1777901212&promo-type-name=promo-code&businessId=208326358",
 "4": "https://market.yandex.ru/search?shopPromoId=1164563_MPC_1779090480&promo-type-name=promo-code&businessId=1164563",
 "5": "https://market.yandex.ru/search?shopPromoId=63895252_U1VFW3WP&promo-type-name=promo-code&businessId=63895252",
 "6": "https://market.yandex.ru/search?shopPromoId=758035_MPC_1778575482&promo-type-name=promo-code&businessId=758035",
 "7": "https://market.yandex.ru/search?shopPromoId=11458987_MPC_1774015058&promo-type-name=promo-code&businessId=11458987",
 "8": "https://market.yandex.ru/search?shopPromoId=86304893_MPC_1768235515&promo-type-name=promo-code&businessId=86304893",
 "9": "https://market.yandex.ru/search?shopPromoId=695681_1U600XPS&promo-type-name=promo-code&businessId=695681",
 "10": "https://market.yandex.ru/search?shopPromoId=864560_MPC_1764314857&promo-type-name=promo-code&businessId=864560",
 "11": "https://market.yandex.ru/search?shopPromoId=751802_316D1W1A&promo-type-name=promo-code&businessId=751802",
 "12": "https://market.yandex.ru/search?shopPromoId=914817_AMDWWTVH&promo-type-name=promo-code&businessId=914817",
 "13": "https://market.yandex.ru/search?shopPromoId=108483739_YU7YB2C9&promo-type-name=promo-code&businessId=108483739",
 "14": "https://market.yandex.ru/search?shopPromoId=950562_MPC_1777896989&promo-type-name=promo-code&businessId=950562",
 "15": "https://market.yandex.ru/search?shopPromoId=2830531_MPC_1777373028&promo-type-name=promo-code&businessId=2830531",
 "16": "https://market.yandex.ru/search?shopPromoId=2830531_MPC_1777818431&promo-type-name=promo-code&businessId=2830531",
 "17": "https://market.yandex.ru/search?shopPromoId=1224751_MPC_1777297438&promo-type-name=promo-code&businessId=1224751&promoKey=zxUNxtyhoEIBiRadHw75Mg",
 "18": "https://market.yandex.ru/search?shopPromoId=172028973_5YVW6U7N&promo-type-name=promo-code&businessId=172028973"
}